pywhois2/__init__.py
pywhois2/common.py
pywhois2/whois.py
pywhois2/whois_parser.py
pywhois2/whois_request.py
pywhois2/data/README.jp.md
pywhois2/data/README.md
pywhois2/data/cctld.yml
pywhois2/data/cctld_jp.yaml
pywhois2/data/data.yml
pywhois2/data/data.ymlz
pywhois2/data/gtld.yml
pywhois2/data/other.yml
pywhois2/templates/ae.tpl
pywhois2/templates/ae.ttp
pywhois2/templates/afnic.tpl
pywhois2/templates/ai.tpl
pywhois2/templates/ai.ttp
pywhois2/templates/am.tpl
pywhois2/templates/ar.tpl
pywhois2/templates/as.tpl
pywhois2/templates/at.tpl
pywhois2/templates/au.tpl
pywhois2/templates/aw.tpl
pywhois2/templates/ax.tpl
pywhois2/templates/be.tpl
pywhois2/templates/bg.tpl
pywhois2/templates/bn.tpl
pywhois2/templates/br.tpl
pywhois2/templates/bw.tpl
pywhois2/templates/by.tpl
pywhois2/templates/cl.tpl
pywhois2/templates/cn.tpl
pywhois2/templates/common.tpl
pywhois2/templates/common.ttp
pywhois2/templates/common_2.tpl
pywhois2/templates/common_iana.tpl
pywhois2/templates/common_iana.ttp
pywhois2/templates/common_relay.tpl
pywhois2/templates/common_relay.ttp
pywhois2/templates/de.tpl
pywhois2/templates/dk.tpl
pywhois2/templates/ee.tpl
pywhois2/templates/eu.tpl
pywhois2/templates/fi.tpl
pywhois2/templates/ge.tpl
pywhois2/templates/gf.tpl
pywhois2/templates/gg.tpl
pywhois2/templates/hk.tpl
pywhois2/templates/hu.tpl
pywhois2/templates/id.tpl
pywhois2/templates/il.tpl
pywhois2/templates/im.tpl
pywhois2/templates/ir.tpl
pywhois2/templates/is.tpl
pywhois2/templates/it.tpl
pywhois2/templates/java_whois_server.tpl
pywhois2/templates/je.tpl
pywhois2/templates/jp.tpl
pywhois2/templates/jp.ttp
pywhois2/templates/kg.tpl
pywhois2/templates/kr.tpl
pywhois2/templates/kz.tpl
pywhois2/templates/lt.tpl
pywhois2/templates/lu.tpl
pywhois2/templates/lv.tpl
pywhois2/templates/md.tpl
pywhois2/templates/mo.tpl
pywhois2/templates/mq.tpl
pywhois2/templates/mx.tpl
pywhois2/templates/nc.tpl
pywhois2/templates/nl.tpl
pywhois2/templates/no.tpl
pywhois2/templates/nu.tpl
pywhois2/templates/om.tpl
pywhois2-0.1.2.dist-info/LICENSE
pywhois2-0.1.2.dist-info/METADATA
pywhois2-0.1.2.dist-info/WHEEL
pywhois2-0.1.2.dist-info/entry_points.txt
pywhois2-0.1.2.dist-info/top_level.txt
pywhois2-0.1.2.dist-info/RECORD
