Metadata-Version: 2.1
Name: pywhois2
Version: 0.1.2
Home-page: https://github.com/blacknon/pywhois2
Author: blacknon
Author-email: blacknon@orebibou.com
Maintainer: blacknon
Maintainer-email: blacknon@orebibou.com
License: MIT License
Classifier: Programming Language :: Python :: 3
Classifier: Programming Language :: Python :: 3.7
Classifier: Programming Language :: Python :: 3.8
Classifier: Programming Language :: Python :: 3.9
Classifier: Programming Language :: Python :: 3.10
Classifier: Programming Language :: Python :: 3.11
Classifier: License :: OSI Approved :: MIT License
License-File: LICENSE
Requires-Dist: pyyaml
Requires-Dist: ipaddress
Requires-Dist: tld
Requires-Dist: stringcase
